UART using verilog with FPGA/receiver.v
// Module: receiver
// Description: Implements a UART receiver that uses an FSM to handle data reception.
// It supports oversampling and handles synchronization issues by checking the received data
// across multiple clock cycles. The receiver processes data only when enabled by Rx_en.

module receiver (
    input wire Rx,             // Serial input receiving data
    input wire Rx_en,          // Receiver enable signal
    output reg ready,          // Signal to indicate data is ready to be read
    input wire ready_clr,      // Signal to clear the ready state
    input wire clk_50m,        // System clock
    input wire clken,          // Clock enable for controlling reception timing
    output reg [7:0] data      // Output data register
);

    // Initialize ready and data signals
    initial begin
        ready = 1'b0;          // Set ready to 0 initially
        data = 8'b0;           // Clear data initially
    end

    // Define states for the reception process
    parameter RX_STATE_START = 2'b00;  // Waiting for start bit
    parameter RX_STATE_DATA  = 2'b01;  // Receiving data bits
    parameter RX_STATE_STOP  = 2'b10;  // Checking stop bit

    // Internal state registers
    reg [1:0] state = RX_STATE_START;  // Initial state
    reg [3:0] sample = 0;              // Sample counter
    reg [3:0] bit_pos = 0;             // Position in the data byte being received
    reg [7:0] scratch = 8'b0;          // Temporary storage for the incoming data

    // Process incoming data on the positive edge of the system clock
    always @(posedge clk_50m) begin
        if (ready_clr)
            ready <= 1'b0;  // Reset ready signal when cleared

        if (clken && ~Rx_en) begin  // Only process data if clock is enabled and Rx is not enabled
            case (state)
                RX_STATE_START: begin  // Handle the start bit
                    if (!Rx || sample != 0)  // Check for the start condition
                        sample <= sample + 1;  // Increment sample counter
                    if (sample == 15) begin  // If a full bit has been sampled
                        state <= RX_STATE_DATA;  // Move to data receiving state
                        bit_pos <= 0;  // Reset bit position
                        sample <= 0;   // Reset sample counter
                        scratch <= 0;  // Clear scratch register
                    end
                end
                RX_STATE_DATA: begin  // Handle data reception
                    sample <= sample + 1;  // Increment sample counter
                    if (sample == 8) begin  // Midpoint of data bit sampling
                        scratch[bit_pos[2:0]] <= Rx;  // Store bit in scratch register
                        bit_pos <= bit_pos + 1;  // Move to the next bit
                    end
                    if (bit_pos == 8 && sample == 15)  // If last bit sampled
                        state <= RX_STATE_STOP;  // Move to stop bit verification
                end
                RX_STATE_STOP: begin  // Handle stop bit
                    if (sample == 15 || (sample >= 8 && !Rx)) begin  // Verify stop bit condition
                        state <= RX_STATE_START;  // Reset to start for new transmission
                        data <= scratch;  // Transfer received data
                        ready <= 1'b1;  // Indicate that data is ready
                        sample <= 0;  // Reset sample counter
                    end else
                        sample <= sample + 1;  // Continue sampling stop bit
                end
                default: begin  // Default case to handle unexpected states
                    state <= RX_STATE_START;  // Reset to initial state
                end
            endcase
        end
    end

endmodule

fpga/transmitter.v
// Module: transmitter
// Description: This module simulates the behavior of a UART transmitter.
// It takes an 8-bit data input and transmits it serially based on clock and enable signals.
// The transmission process involves four states: IDLE, START, DATA, and STOP.

module transmitter(
    input wire [7:0] data_in,  // 8-bit input data to be transmitted
    input wire Tx_en,          // Transmit enable signal
    input wire clk_50m,        // 50 MHz clock signal
    input wire clken,          // Clock enable for controlling transmission timing
    output reg Tx,             // Serial output transmitting data bit-by-bit
    output wire Tx_busy        // Signal indicating the transmitter is busy
);

    // Initial condition: Set the transmission line to high (idle state)
    initial begin
        Tx = 1'b1; 
    end

    // State definitions using 2-bit encoding for the finite state machine (FSM)
    parameter TX_STATE_IDLE  = 2'b00;  // IDLE state: waiting for enable signal
    parameter TX_STATE_START = 2'b01;  // START state: start bit transmission
    parameter TX_STATE_DATA  = 2'b10;  // DATA state: data bits transmission
    parameter TX_STATE_STOP  = 2'b11;  // STOP state: stop bit transmission to complete the cycle

    // Internal registers
    reg [7:0] data = 8'h00;          // Buffer to hold data being transmitted
    reg [2:0] bit_pos = 3'h0;        // Bit position counter for data transmission
    reg [1:0] state = TX_STATE_IDLE; // Current state of the FSM

    // FSM for controlling transmission based on state and clock signals
    always @(posedge clk_50m) begin
        case (state)
            TX_STATE_IDLE: begin  // Wait for enable signal to start transmission
                if (~Tx_en) begin
                    state <= TX_STATE_START;
                    data <= data_in;   // Load data from input
                    bit_pos <= 3'h0;   // Reset bit position
                end
            end
            TX_STATE_START: begin  // Transmit start bit (logic low)
                if (clken) begin
                    Tx <= 1'b0;
                    state <= TX_STATE_DATA;
                end
            end
            TX_STATE_DATA: begin  // Transmit data bits
                if (clken) begin
                    Tx <= data[bit_pos];
                    bit_pos <= bit_pos + 1;
                    if (bit_pos == 3'h7)  // Check if all bits are transmitted
                        state <= TX_STATE_STOP;
                end
            end
            TX_STATE_STOP: begin  // Transmit stop bit (logic high) and return to idle
                if (clken) begin
                    Tx <= 1'b1;
                    state <= TX_STATE_IDLE;
                end
            end
            default: begin  // Default case to handle unexpected states
                Tx <= 1'b1;  // Ensure line is idle
                state <= TX_STATE_IDLE;
            end
        endcase
    end

    // Output busy signal when the transmitter is not in IDLE state
    assign Tx_busy = (state != TX_STATE_IDLE);

endmodule

UART using verilog with FPGA 2nd/baudrate.v
// Module: baudrate
// Description: This module divides a 50 MHz input clock to generate enable signals
// for both transmitting (Tx) and receiving (Rx) that operate at a baud rate of 115200.
// The Rx clock is additionally oversampled by 16x to increase the reliability of data reception.

module baudrate(
    input wire clk_50m,       // Input clock at 50 MHz
    output wire Rxclk_en,     // Enable signal for the Rx clock, oversampled
    output wire Txclk_en      // Enable signal for the Tx clock
);

    // Parameters for calculating the number of clock cycles per baud bit
    parameter RX_ACC_MAX = 50000000 / (115200 * 16); // Calculate max count for Rx oversampled by 16x
    parameter TX_ACC_MAX = 50000000 / 115200;        // Calculate max count for Tx
    parameter RX_ACC_WIDTH = $clog2(RX_ACC_MAX);     // Determine bit width needed for Rx accumulator
    parameter TX_ACC_WIDTH = $clog2(TX_ACC_MAX);     // Determine bit width needed for Tx accumulator

    // Accumulators for baud rate generation
    reg [RX_ACC_WIDTH - 1:0] rx_acc = 0;  // Rx accumulator, initialized to 0
    reg [TX_ACC_WIDTH - 1:0] tx_acc = 0;  // Tx accumulator, initialized to 0

    // Generate Rx and Tx clock enable signals
    // Enable signals are active when accumulators reset
    assign Rxclk_en = (rx_acc == 0);
    assign Txclk_en = (tx_acc == 0);

    // Baud rate clock generation for Rx
    // This clock is oversampled by 16x for better sampling of incoming data
    always @(posedge clk_50m) begin
        if (rx_acc == RX_ACC_MAX - 1)  // Check if the accumulator has reached its max value
            rx_acc <= 0;               // Reset the accumulator
        else
            rx_acc <= rx_acc + 1;      // Increment the accumulator
    end

    // Baud rate clock generation for Tx
    // This clock matches the baud rate of 115200 for data transmission
    always @(posedge clk_50m) begin
        if (tx_acc == TX_ACC_MAX - 1)  // Check if the accumulator has reached its max value
            tx_acc <= 0;               // Reset the accumulator
        else
            tx_acc <= tx_acc + 1;      // Increment the accumulator
    end

endmodule

UART using verilog with FPGA/uart.v
// Module: uart
// Description: This module integrates the components of a UART interface including
// a baud rate generator, a transmitter, and a receiver. It handles both transmitting
// and receiving data at a specified baud rate, controlled by enabling signals. 

module uart(
    input wire [7:0] data_in,   // 8-bit input data to be transmitted
    input wire Tx_en,           // Enable signal for transmitter
    input wire clear,           // Not used in this instantiation (consider removal if not required)
    input wire clk_50m,         // System clock at 50 MHz
    output wire Tx,             // Transmitted serial data output
    output wire Tx_busy,        // Signal indicating transmitter is busy
    input wire Rx,              // Received serial data input
    input wire Rx_en,           // Enable signal for receiver
    output wire ready,          // Signal to indicate data is ready to be read
    input wire ready_clr,       // Signal to clear the ready state
    output wire [7:0] data_out, // 8-bit output data received
    output [7:0] LEDR,          // LED output directly reflecting input data (for debugging or status)
    output wire Tx2             // Duplicate of Tx for additional interfacing
);

    // Assign LEDs to mirror input data for visual debugging or demonstration
    assign LEDR = data_in;

    // Duplicate the Tx signal to an additional output pin for further use
    assign Tx2 = Tx;

    // Internal connections for baud rate enable signals
    wire Txclk_en, Rxclk_en;

    // Instantiate the baud rate generator
    baudrate uart_baud(
        .clk_50m(clk_50m),
        .Rxclk_en(Rxclk_en),    // Enable signal for the receiver clock
        .Txclk_en(Txclk_en)     // Enable signal for the transmitter clock
    );

    // Instantiate the transmitter module
    transmitter uart_Tx(
        .data_in(data_in),
        .Tx_en(Tx_en),
        .clk_50m(clk_50m),
        .clken(Txclk_en),       // Use Tx clock enable for transmitter operation
        .Tx(Tx),
        .Tx_busy(Tx_busy)
    );

    // Instantiate the receiver module
    receiver uart_Rx(
        .Rx(Rx),
        .Rx_en(Rx_en),
        .ready(ready),
        .ready_clr(ready_clr),
        .clk_50m(clk_50m),
        .clken(Rxclk_en),       // Use Rx clock enable for receiver operation
        .data(data_out)
    );

endmodule

fpga/uart_TB.v
// Testbench Module: uart_TB
// Description: This testbench is designed to verify the functionality of a UART module 
// by implementing a serial loopback. It transmits data bytes and checks if the received 
// data matches the transmitted data. This ensures both the transmitter and receiver 
// components of the UART are functioning correctly.

//`include "uart.v" // Include the UART module definition

module uart_TB();

    // Testbench control signals
    reg [7:0] data = 0;      // Data to be transmitted
    reg clk = 0;             // Test clock signal
    reg enable = 0;          // Enable signal for transmitter
    reg Rx_en = 0;           // Enable signal for receiver

    // UART module outputs to be monitored
    wire Tx_busy;            // Indicates if the transmitter is busy
    wire ready;              // Indicates if the receiver has data ready
    wire [7:0] Rx_data;      // Holds the data received from the UART

    // Loopback wire for connecting Tx and Rx internally
    wire loopback;
    reg ready_clr = 0;       // Signal to clear the 'ready' flag in the receiver

    // Instantiation of the UART module
    uart test_uart(
        .data_in(data),
        .Tx_en(enable),
        .clk_50m(clk),
        .Tx(loopback),
        .Tx_busy(Tx_busy),
        .Rx(loopback),
        .ready(ready),
        .ready_clr(ready_clr),
        .Rx_en(Rx_en),       // Connect the Rx_en signal
        .data_out(Rx_data)
    );

    // Initial block to setup and start the test
    initial begin
        $dumpfile("uart.vcd");  // Set up the VCD file for waveform analysis
        $dumpvars(0, uart_TB);  // Record simulation data for all variables in the testbench
        
        // Initial state of control signals
        enable <= 1'b1;  // Initially enable the transmitter
        Rx_en <= 1'b1;   // Initially enable the receiver
        #2 enable <= 1'b0;  // Disable after a short delay to simulate a transmission trigger
        #2 Rx_en <= 1'b0;   // Disable after a short delay
    end

    // Clock generation
    always begin
        #1 clk = ~clk;  // Toggle the clock every time unit to simulate a 50MHz clock
    end

    // Check the received data when it is ready
    always @(posedge ready) begin
        #2 ready_clr <= 1;  // Clear the ready signal after a delay to process the received data
        #2 ready_clr <= 0;  // Reset the ready clear signal
        if (Rx_data != data) begin
            // If the received data does not match the sent data, print an error message
            $display("FAIL: rx data %x does not match tx %x", Rx_data, data);
            //$finish;  // End the simulation
        end else begin
            // Check for specific data value to determine end of the test
            if (Rx_data == 8'h2) begin  // Arbitrary end condition based on expected test data sequence
                $display("SUCCESS: all bytes verified");
                //$finish;  // End the simulation on success
            end
            // Prepare for the next test iteration
            data <= data + 1'b1;  // Increment the data to send
            enable <= 1'b1;       // Re-enable the transmitter
            Rx_en <= 1'b1;        // Re-enable the receiver
            #2 enable <= 1'b0;    // Toggle enable signals to mimic behavior
            #2 Rx_en <= 1'b0;
        end
    end
endmodule

UART using verilog with FPGA/simulation/modelsim/uart.vcd
$date
	Wed May 08 09:16:07 2024
$end
$version
	ModelSim Version 10.1d
$end
$timescale
	1ps
$end
$scope module uart_TB $end
$var reg 8 ! data [7:0] $end
$var reg 1 " clk $end
$var reg 1 # enable $end
$var reg 1 $ Rx_en $end
$var wire 1 % Tx_busy $end
$var wire 1 & ready $end
$var wire 1 ' Rx_data [7] $end
$var wire 1 ( Rx_data [6] $end
$var wire 1 ) Rx_data [5] $end
$var wire 1 * Rx_data [4] $end
$var wire 1 + Rx_data [3] $end
$var wire 1 , Rx_data [2] $end
$var wire 1 - Rx_data [1] $end
$var wire 1 . Rx_data [0] $end
$var wire 1 / loopback $end
$var reg 1 0 ready_clr $end
$scope module test_uart $end
$var wire 1 1 data_in [7] $end
$var wire 1 2 data_in [6] $end
$var wire 1 3 data_in [5] $end
$var wire 1 4 data_in [4] $end
$var wire 1 5 data_in [3] $end
$var wire 1 6 data_in [2] $end
$var wire 1 7 data_in [1] $end
$var wire 1 8 data_in [0] $end
$var wire 1 9 Tx_en $end
$var wire 1 : clear $end
$var wire 1 ; clk_50m $end
$var wire 1 / Tx $end
$var wire 1 % Tx_busy $end
$var wire 1 / Rx $end
$var wire 1 < Rx_en $end
$var wire 1 & ready $end
$var wire 1 = ready_clr $end
$var wire 1 ' data_out [7] $end
$var wire 1 ( data_out [6] $end
$var wire 1 ) data_out [5] $end
$var wire 1 * data_out [4] $end
$var wire 1 + data_out [3] $end
$var wire 1 , data_out [2] $end
$var wire 1 - data_out [1] $end
$var wire 1 . data_out [0] $end
$var wire 1 > LEDR [7] $end
$var wire 1 ? LEDR [6] $end
$var wire 1 @ LEDR [5] $end
$var wire 1 A LEDR [4] $end
$var wire 1 B LEDR [3] $end
$var wire 1 C LEDR [2] $end
$var wire 1 D LEDR [1] $end
$var wire 1 E LEDR [0] $end
$var wire 1 F Tx2 $end
$var wire 1 G Txclk_en $end
$var wire 1 H Rxclk_en $end
$scope module uart_baud $end
$var parameter 32 I RX_ACC_MAX $end
$var parameter 32 J TX_ACC_MAX $end
$var parameter 32 K RX_ACC_WIDTH $end
$var parameter 32 L TX_ACC_WIDTH $end
$var wire 1 ; clk_50m $end
$var wire 1 H Rxclk_en $end
$var wire 1 G Txclk_en $end
$var reg 5 M rx_acc [4:0] $end
$var reg 9 N tx_acc [8:0] $end
$upscope $end
$scope module uart_Tx $end
$var parameter 2 O TX_STATE_IDLE $end
$var parameter 2 P TX_STATE_START $end
$var parameter 2 Q TX_STATE_DATA $end
$var parameter 2 R TX_STATE_STOP $end
$var wire 1 1 data_in [7] $end
$var wire 1 2 data_in [6] $end
$var wire 1 3 data_in [5] $end
$var wire 1 4 data_in [4] $end
$var wire 1 5 data_in [3] $end
$var wire 1 6 data_in [2] $end
$var wire 1 7 data_in [1] $end
$var wire 1 8 data_in [0] $end
$var wire 1 9 Tx_en $end
$var wire 1 ; clk_50m $end
$var wire 1 G clken $end
$var reg 1 S Tx $end
$var wire 1 % Tx_busy $end
$var reg 8 T data [7:0] $end
$var reg 3 U bit_pos [2:0] $end
$var reg 2 V state [1:0] $end
$upscope $end
$scope module uart_Rx $end
$var parameter 2 W RX_STATE_START $end
$var parameter 2 X RX_STATE_DATA $end
$var parameter 2 Y RX_STATE_STOP $end
$var wire 1 / Rx $end
$var wire 1 < Rx_en $end
$var reg 1 Z ready $end
$var wire 1 = ready_clr $end
$var wire 1 ; clk_50m $end
$var wire 1 H clken $end
$var reg 8 [ data [7:0] $end
$var reg 2 \ state [1:0] $end
$var reg 4 ] sample [3:0] $end
$var reg 4 ^ bit_pos [3:0] $end
$var reg 8 _ scratch [7:0] $end
$upscope $end
$upscope $end
$upscope $end
$enddefinitions $end
#0
$dumpvars
b0 !
0"
1#
1$
00
b0 M
b0 N
1S
b0 T
b0 U
b0 V
0Z
b0 [
b0 \
b0 ]
b0 ^
b0 _
b11011 I
b110110010 J
b101 K
b1001 L
b0 O
b1 P
b10 Q
b11 R
b0 W
b1 X
b10 Y
0%
0&
0.
0-
0,
0+
0*
0)
0(
0'
1/
1G
1H
1<
0=
0;
19
08
07
06
05
04
03
02
01
z:
0E
0D
0C
0B
0A
0@
0?
0>
1F
$end
#1
1"
1;
b1 M
b1 N
0H
0G
#2
0"
0;
0#
09
#3
1"
1;
b10 M
b10 N
b1 V
1%
#4
0"
0;
0$
0<
#5
1"
1;
b11 M
b11 N
#6
0"
0;
#7
1"
1;
b100 M
b100 N
#8
0"
0;
#9
1"
1;
b101 M
b101 N
#10
0"
0;
#11
1"
1;
b110 M
b110 N
#12
0"
0;
#13
1"
1;
b111 M
b111 N
#14
0"
0;
#15
1"
1;
b1000 M
b1000 N
#16
0"
0;
#17
1"
1;
b1001 M
b1001 N
#18
0"
0;
#19
1"
1;
b1010 M
b1010 N
#20
0"
0;
#21
1"
1;
b1011 M
b1011 N
#22
0"
0;
#23
1"
1;
b1100 M
b1100 N
#24
0"
0;
#25
1"
1;
b1101 M
b1101 N
#26
0"
0;
#27
1"
1;
b1110 M
b1110 N
#28
0"
0;
#29
1"
1;
b1111 M
b1111 N
#30
0"
0;
#31
1"
1;
b10000 M
b10000 N
#32
0"
0;
#33
1"
1;
b10001 M
b10001 N
#34
0"
0;
#35
1"
1;
b10010 M
b10010 N
#36
0"
0;
#37
1"
1;
b10011 M
b10011 N
#38
0"
0;
#39
1"
1;
b10100 M
b10100 N
#40
0"
0;
#41
1"
1;
b10101 M
b10101 N
#42
0"
0;
#43
1"
1;
b10110 M
b10110 N
#44
0"
0;
#45
1"
1;
b10111 M
b10111 N
#46
0"
0;
#47
1"
1;
b11000 M
b11000 N
#48
0"
0;
#49
1"
1;
b11001 M
b11001 N
#50
0"
0;
#51
1"
1;
b11010 M
b11010 N
#52
0"
0;
#53
1"
1;
b0 M
b11011 N
1H
#54
0"
0;
#55
1"
1;
b1 M
b11100 N
0H
#56
0"
0;
#57
1"
1;
b10 M
b11101 N
#58
0"
0;
#59
1"
1;
b11 M
b11110 N
#60
0"
0;
#61
1"
1;
b100 M
b11111 N
#62
0"
0;
#63
1"
1;
b101 M
b100000 N
#64
0"
0;
#65
1"
1;
b110 M
b100001 N
#66
0"
0;
#67
1"
1;
b111 M
b100010 N
#68
0"
0;
#69
1"
1;
b1000 M
b100011 N
#70
0"
0;
#71
1"
1;
b1001 M
b100100 N
#72
0"
0;
#73
1"
1;
b1010 M
b100101 N
#74
0"
0;
#75
1"
1;
b1011 M
b100110 N
#76
0"
0;
#77
1"
1;
b1100 M
b100111 N
#78
0"
0;
#79
1"
1;
b1101 M
b101000 N
#80
0"
0;
#81
1"
1;
b1110 M
b101001 N
#82
0"
0;
#83
1"
1;
b1111 M
b101010 N
#84
0"
0;
#85
1"
1;
b10000 M
b101011 N
#86
0"
0;
#87
1"
1;
b10001 M
b101100 N
#88
0"
0;
#89
1"
1;
b10010 M
b101101 N
#90
0"
0;
#91
1"
1;
b10011 M
b101110 N
#92
0"
0;
#93
1"
1;
b10100 M
b101111 N
#94
0"
0;
#95
1"
1;
b10101 M
b110000 N
#96
0"
0;
#97
1"
1;
b10110 M
b110001 N
#98
0"
0;
#99
1"
1;
b10111 M
b110010 N
#100
0"
0;
#101
1"
1;
b11000 M
b110011 N
#102
0"
0;
#103
1"
1;
b11001 M
b110100 N
#104
0"
0;
#105
1"
1;
b11010 M
b110101 N
#106
0"
0;
#107
1"
1;
b0 M
b110110 N
1H
#108
0"
0;
#109
1"
1;
b1 M
b110111 N
0H
#110
0"
0;
#111
1"
1;
b10 M
b111000 N
#112
0"
0;
#113
1"
1;
b11 M
b111001 N
#114
0"
0;
#115
1"
1;
b100 M
b111010 N
#116
0"
0;
#117
1"
1;
b101 M
b111011 N
#118
0"
0;
#119
1"
1;
b110 M
b111100 N
#120
0"
0;
#121
1"
1;
b111 M
b111101 N
#122
0"
0;
#123
1"
1;
b1000 M
b111110 N
#124
0"
0;
#125
1"
1;
b1001 M
b111111 N
#126
0"
0;
#127
1"
1;
b1010 M
b1000000 N
#128
0"
0;
#129
1"
1;
b1011 M
b1000001 N
#130
0"
0;
#131
1"
1;
b1100 M
b1000010 N
#132
0"
0;
#133
1"
1;
b1101 M
b1000011 N
#134
0"
0;
#135
1"
1;
b1110 M
b1000100 N
#136
0"
0;
#137
1"
1;
b1111 M
b1000101 N
#138
0"
0;
#139
1"
1;
b10000 M
b1000110 N
#140
0"
0;
#141
1"
1;
b10001 M
b1000111 N
#142
0"
0;
#143
1"
1;
b10010 M
b1001000 N
#144
0"
0;
#145
1"
1;
b10011 M
b1001001 N
#146
0"
0;
#147
1"
1;
b10100 M
b1001010 N
#148
0"
0;
#149
1"
1;
b10101 M
b1001011 N
#150
0"
0;
#151
1"
1;
b10110 M
b1001100 N
#152
0"
0;
#153
1"
1;
b10111 M
b1001101 N
#154
0"
0;
#155
1"
1;
b11000 M
b1001110 N
#156
0"
0;
#157
1"
1;
b11001 M
b1001111 N
#158
0"
0;
#159
1"
1;
b11010 M
b1010000 N
#160
0"
0;
#161
1"
1;
b0 M
b1010001 N
1H
#162
0"
0;
#163
1"
1;
b1 M
b1010010 N
0H
#164
0"
0;
#165
1"
1;
b10 M
b1010011 N
#166
0"
0;
#167
1"
1;
b11 M
b1010100 N
#168
0"
0;
#169
1"
1;
b100 M
b1010101 N
#170
0"
0;
#171
1"
1;
b101 M
b1010110 N
#172
0"
0;
#173
1"
1;
b110 M
b1010111 N
#174
0"
0;
#175
1"
1;
b111 M
b1011000 N
#176
0"
0;
#177
1"
1;
b1000 M
b1011001 N
#178
0"
0;
#179
1"
1;
b1001 M
b1011010 N
#180
0"
0;
#181
1"
1;
b1010 M
b1011011 N
#182
0"
0;
#183
1"
1;
b1011 M
b1011100 N
#184
0"
0;
#185
1"
1;
b1100 M
b1011101 N
#186
0"
0;
#187
1"
1;
b1101 M
b1011110 N
#188
0"
0;
#189
1"
1;
b1110 M
b1011111 N
#190
0"
0;
#191
1"
1;
b1111 M
b1100000 N
#192
0"
0;
#193
1"
1;
b10000 M
b1100001 N
#194
0"
0;
#195
1"
1;
b10001 M
b1100010 N
#196
0"
0;
#197
1"
1;
b10010 M
b1100011 N
#198
0"
0;
#199
1"
1;
b10011 M
b1100100 N
#200
0"
0;
#201
1"
1;
b10100 M
b1100101 N
#202
0"
0;
#203
1"
1;
b10101 M
b1100110 N
#204
0"
0;
#205
1"
1;
b10110 M
b1100111 N
#206
0"
0;
#207
1"
1;
b10111 M
b1101000 N
#208
0"
0;
#209
1"
1;
b11000 M
b1101001 N
#210
0"
0;
#211
1"
1;
b11001 M
b1101010 N
#212
0"
0;
#213
1"
1;
b11010 M
b1101011 N
#214
0"
0;
#215
1"
1;
b0 M
b1101100 N
1H
#216
0"
0;
#217
1"
1;
b1 M
b1101101 N
0H
#218
0"
0;
#219
1"
1;
b10 M
b1101110 N
#220
0"
0;
#221
1"
1;
b11 M
b1101111 N
#222
0"
0;
#223
1"
1;
b100 M
b1110000 N
#224
0"
0;
#225
1"
1;
b101 M
b1110001 N
#226
0"
0;
#227
1"
1;
b110 M
b1110010 N
#228
0"
0;
#229
1"
1;
b111 M
b1110011 N
#230
0"
0;
#231
1"
1;
b1000 M
b1110100 N
#232
0"
0;
#233
1"
1;
b1001 M
b1110101 N
#234
0"
0;
#235
1"
1;
b1010 M
b1110110 N
#236
0"
0;
#237
1"
1;
b1011 M
b1110111 N
#238
0"
0;
#239
1"
1;
b1100 M
b1111000 N
#240
0"
0;
#241
1"
1;
b1101 M
b1111001 N
#242
0"
0;
#243
1"
1;
b1110 M
b1111010 N
#244
0"
0;
#245
1"
1;
b1111 M
b1111011 N
#246
0"
0;
#247
1"
1;
b10000 M
b1111100 N
#248
0"
0;
#249
1"
1;
b10001 M
b1111101 N
#250
0"
0;
#251
1"
1;
b10010 M
b1111110 N
#252
0"
0;
#253
1"
1;
b10011 M
b1111111 N
#254
0"
0;
#255
1"
1;
b10100 M
b10000000 N
#256
0"
0;
#257
1"
1;
b10101 M
b10000001 N
#258
0"
0;
#259
1"
1;
b10110 M
b10000010 N
#260
0"
0;
#261
1"
1;
b10111 M
b10000011 N
#262
0"
0;
#263
1"
1;
b11000 M
b10000100 N
#264
0"
0;
#265
1"
1;
b11001 M
b10000101 N
#266
0"
0;
#267
1"
1;
b11010 M
b10000110 N
#268
0"
0;
#269
1"
1;
b0 M
b10000111 N
1H
#270
0"
0;
#271
1"
1;
b1 M
b10001000 N
0H
#272
0"
0;
#273
1"
1;
b10 M
b10001001 N
#274
0"
0;
#275
1"
1;
b11 M
b10001010 N
#276
0"
0;
#277
1"
1;
b100 M
b10001011 N
#278
0"
0;
#279
1"
1;
b101 M
b10001100 N
#280
0"
0;
#281
1"
1;
b110 M
b10001101 N
#282
0"
0;
#283
1"
1;
b111 M
b10001110 N
#284
0"
0;
#285
1"
1;
b1000 M
b10001111 N
#286
0"
0;
#287
1"
1;
b1001 M
b10010000 N
#288
0"
0;
#289
1"
1;
b1010 M
b10010001 N
#290
0"
0;
#291
1"
1;
b1011 M
b10010010 N
#292
0"
0;
#293
1"
1;
b1100 M
b10010011 N
#294
0"
0;
#295
1"
1;
b1101 M
b10010100 N
#296
0"
0;
#297
1"
1;
b1110 M
b10010101 N
#298
0"
0;
#299
1"
1;
b1111 M
b10010110 N
#300
0"
0;
#301
1"
1;
b10000 M
b10010111 N
#302
0"
0;
#303
1"
1;
b10001 M
b10011000 N
#304
0"
0;
#305
1"
1;
b10010 M
b10011001 N
#306
0"
0;
#307
1"
1;
b10011 M
b10011010 N
#308
0"
0;
#309
1"
1;
b10100 M
b10011011 N
#310
0"
0;
#311
1"
1;
b10101 M
b10011100 N
#312
0"
0;
#313
1"
1;
b10110 M
b10011101 N
#314
0"
0;
#315
1"
1;
b10111 M
b10011110 N
#316
0"
0;
#317
1"
1;
b11000 M
b10011111 N
#318
0"
0;
#319
1"
1;
b11001 M
b10100000 N
#320
0"
0;
#321
1"
1;
b11010 M
b10100001 N
#322
0"
0;
#323
1"
1;
b0 M
b10100010 N
1H
#324
0"
0;
#325
1"
1;
b1 M
b10100011 N
0H
#326
0"
0;
#327
1"
1;
b10 M
b10100100 N
#328
0"
0;
#329
1"
1;
b11 M
b10100101 N
#330
0"
0;
#331
1"
1;
b100 M
b10100110 N
#332
0"
0;
#333
1"
1;
b101 M
b10100111 N
#334
0"
0;
#335
1"
1;
b110 M
b10101000 N
#336
0"
0;
#337
1"
1;
b111 M
b10101001 N
#338
0"
0;
#339
1"
1;
b1000 M
b10101010 N
#340
0"
0;
#341
1"
1;
b1001 M
b10101011 N
#342
0"
0;
#343
1"
1;
b1010 M
b10101100 N
#344
0"
0;
#345
1"
1;
b1011 M
b10101101 N
#346
0"
0;
#347
1"
1;
b1100 M
b10101110 N
#348
0"
0;
#349
1"
1;
b1101 M
b10101111 N
#350
0"
0;
#351
1"
1;
b1110 M
b10110000 N
#352
0"
0;
#353
1"
1;
b1111 M
b10110001 N
#354
0"
0;
#355
1"
1;
b10000 M
b10110010 N
#356
0"
0;
#357
1"
1;
b10001 M
b10110011 N
#358
0"
0;
#359
1"
1;
b10010 M
b10110100 N
#360
0"
0;
#361
1"
1;
b10011 M
b10110101 N
#362
0"
0;
#363
1"
1;
b10100 M
b10110110 N
#364
0"
0;
#365
1"
1;
b10101 M
b10110111 N
#366
0"
0;
#367
1"
1;
b10110 M
b10111000 N
#368
0"
0;
#369
1"
1;
b10111 M
b10111001 N
#370
0"
0;
#371
1"
1;
b11000 M
b10111010 N
#372
0"
0;
#373
1"
1;
b11001 M
b10111011 N
#374
0"
0;
#375
1"
1;
b11010 M
b10111100 N
#376
0"
0;
#377
1"
1;
b0 M
b10111101 N
1H
#378
0"
0;
#379
1"
1;
b1 M
b10111110 N
0H
#380
0"
0;
#381
1"
1;
b10 M
b10111111 N
#382
0"
0;
#383
1"
1;
b11 M
b11000000 N
#384
0"
0;
#385
1"
1;
b100 M
b11000001 N
#386
0"
0;
#387
1"
1;
b101 M
b11000010 N
#388
0"
0;
#389
1"
1;
b110 M
b11000011 N
#390
0"
0;
#391
1"
1;
b111 M
b11000100 N
#392
0"
0;
#393
1"
1;
b1000 M
b11000101 N
#394
0"
0;
#395
1"
1;
b1001 M
b11000110 N
#396
0"
0;
#397
1"
1;
b1010 M
b11000111 N
#398
0"
0;
#399
1"
1;
b1011 M
b11001000 N
#400
0"
0;
#401
1"
1;
b1100 M
b11001001 N
#402
0"
0;
#403
1"
1;
b1101 M
b11001010 N
#404
0"
0;
#405
1"
1;
b1110 M
b11001011 N
#406
0"
0;
#407
1"
1;
b1111 M
b11001100 N
#408
0"
0;
#409
1"
1;
b10000 M
b11001101 N
#410
0"
0;
#411
1"
1;
b10001 M
b11001110 N
#412
0"
0;
#413
1"
1;
b10010 M
b11001111 N
#414
0"
0;
#415
1"
1;
b10011 M
b11010000 N
#416
0"
0;
#417
1"
1;
b10100 M
b11010001 N
#418
0"
0;
#419
1"
1;
b10101 M
b11010010 N
#420
0"
0;
#421
1"
1;
b10110 M
b11010011 N
#422
0"
0;
#423
1"
1;
b10111 M
b11010100 N
#424
0"
0;
#425
1"
1;
b11000 M
b11010101 N
#426
0"
0;
#427
1"
1;
b11001 M
b11010110 N
#428
0"
0;
#429
1"
1;
b11010 M
b11010111 N
#430
0"
0;
#431
1"
1;
b0 M
b11011000 N
1H
#432
0"
0;
#433
1"
1;
b1 M
b11011001 N
0H
#434
0"
0;
#435
1"
1;
b10 M
b11011010 N
#436
0"
0;
#437
1"
1;
b11 M
b11011011 N
#438
0"
0;
#439
1"
1;
b100 M
b11011100 N
#440
0"
0;
#441
1"
1;
b101 M
b11011101 N
#442
0"
0;
#443
1"
1;
b110 M
b11011110 N
#444
0"
0;
#445
1"
1;
b111 M
b11011111 N
#446
0"
0;
#447
1"
1;
b1000 M
b11100000 N
#448
0"
0;
#449
1"
1;
b1001 M
b11100001 N
#450
0"
0;
#451
1"
1;
b1010 M
b11100010 N
#452
0"
0;
#453
1"
1;
b1011 M
b11100011 N
#454
0"
0;
#455
1"
1;
b1100 M
b11100100 N
#456
0"
0;
#457
1"
1;
b1101 M
b11100101 N
#458
0"
0;
#459
1"
1;
b1110 M
b11100110 N
#460
0"
0;
#461
1"
1;
b1111 M
b11100111 N
#462
0"
0;
#463
1"
1;
b10000 M
b11101000 N
#464
0"
0;
#465
1"
1;
b10001 M
b11101001 N
#466
0"
0;
#467
1"
1;
b10010 M
b11101010 N
#468
0"
0;
#469
1"
1;
b10011 M
b11101011 N
#470
0"
0;
#471
1"
1;
b10100 M
b11101100 N
#472
0"
0;
#473
1"
1;
b10101 M
b11101101 N
#474
0"
0;
#475
1"
1;
b10110 M
b11101110 N
#476
0"
0;
#477
1"
1;
b10111 M
b11101111 N
